apmpython/__init__.py
apmpython/apmpython.py
dummytestpythonapm-0.1.5.dist-info/LICENSE
dummytestpythonapm-0.1.5.dist-info/METADATA
dummytestpythonapm-0.1.5.dist-info/WHEEL
dummytestpythonapm-0.1.5.dist-info/top_level.txt
dummytestpythonapm-0.1.5.dist-info/RECORD
